[
    {
        "NEj": "1510344944",
        "NPosteEj": 1,
        "DateModificationEj": "2021-01-05T00:00:00.000Z",
        "CompteBudgetaire": "Dépenses de fonction",
        "ContratEtatRegion": "#",
        "Montant": 0.02,
        "RefCentreCouts": {
            "Id": 95,
            "Code": "BG00/DDCC035035"
        },
        "RefCompteGeneral": {
            "Id": 6,
            "Code": "PCE/6068800000"
        },
        "RefDomaineFonctionnel": {
            "Id": 283,
            "Code": "0206-02-24"
        },
        "RefFournisseurTitulaire": {
            "Id": 14628,
            "Code": "1000001984"
        },
        "RefGroupeMarchandise": {
            "Id": 6,
            "Code": "44.03.14"
        },
        "RefLocalisationInterministerielle": {
            "Id": 2,
            "Code": "N53"
        },
        "RefProgrammation": {
            "Id": 895,
            "Code": "BG00/020602002401"
        },
        "label ref programmation": "Plan urgence epizoo",
        "RefCodeProgramme": {
            "Id": 44,
            "Code": "206"
        },
        "code_programme": "206",
        "nom_programme": "Sécurité et qualité sanitaires de l'alimentation",
        "RefSiret": {
            "Id": 46786,
            "Code": "2725002600021"
        },
        "code_siret": "2725002600021",
        "nom_beneficiaire": null,
        "Commune": null,
        "type_etablissement": null,
        "code_commune": null,
        "Theme": "Agriculture, alimentation, forêt et affaires rurales"
    },
    {
        "NEj": "2201246550",
        "NPosteEj": 5,
        "DateModificationEj": "2021-01-05T00:00:00.000Z",
        "CompteBudgetaire": "Dépenses de fonction",
        "ContratEtatRegion": "#",
        "Montant": 2505.6,
        "RefCentreCouts": {
            "Id": 96,
            "Code": "BG00/DDPP022022"
        },
        "RefCompteGeneral": {
            "Id": 65,
            "Code": "PCE/6135000000"
        },
        "RefDomaineFonctionnel": {
            "Id": 281,
            "Code": "0206-02-20"
        },
        "RefFournisseurTitulaire": {
            "Id": 14683,
            "Code": "2100115535"
        },
        "RefGroupeMarchandise": {
            "Id": 360,
            "Code": "43.01.04"
        },
        "RefLocalisationInterministerielle": {
            "Id": 2,
            "Code": "N53"
        },
        "RefProgrammation": {
            "Id": 898,
            "Code": "BG00/020602002001"
        },
        "label ref programmation": "Malad anim hors ESST",
        "RefCodeProgramme": {
            "Id": 44,
            "Code": "206"
        },
        "code_programme": "206",
        "nom_programme": "Sécurité et qualité sanitaires de l'alimentation",
        "RefSiret": {
            "Id": 46869,
            "Code": "13001898900017"
        },
        "code_siret": "13001898900017",
        "nom_beneficiaire": "INOVALYS",
        "Theme": "Agriculture, alimentation, forêt et affaires rurales",
        "type_etablissement": null,
        "Commune": {
            "Id": 17469,
            "CodeCommune": "49007",
            "LabelCrte": "CRTE Angers Loire Métropole",
            "CodeCrte": "crte-52-49-2"
        },
        "code_commune": "49007"
    },
    {
        "NEj": "1404940468",
        "NPosteEj": 2,
        "DateModificationEj": "2021-01-19T00:00:00.000Z",
        "CompteBudgetaire": "Dépenses de fonction",
        "ContratEtatRegion": "#",
        "Montant": 86.86,
        "RefCentreCouts": {
            "Id": 95,
            "Code": "BG00/DDCC035035"
        },
        "RefCompteGeneral": {
            "Id": 10,
            "Code": "PCE/6188000000"
        },
        "RefDomaineFonctionnel": {
            "Id": 289,
            "Code": "0206-03-31"
        },
        "RefFournisseurTitulaire": {
            "Id": 1081,
            "Code": "1000214549"
        },
        "RefGroupeMarchandise": {
            "Id": 140,
            "Code": "41.05.07"
        },
        "RefLocalisationInterministerielle": {
            "Id": 2,
            "Code": "N53"
        },
        "RefProgrammation": {
            "Id": 902,
            "Code": "BG00/020603003101"
        },
        "label ref programmation": "Inspection sanitaire",
        "RefCodeProgramme": {
            "Id": 44,
            "Code": "206"
        },
        "code_programme": "206",
        "nom_programme": "Sécurité et qualité sanitaires de l'alimentation",
        "RefSiret": {
            "Id": 26840,
            "Code": "77573383500125"
        },
        "code_siret": "77573383500125",
        "nom_beneficiaire": "MAJ",
        "Theme": "Agriculture, alimentation, forêt et affaires rurales",
        "type_etablissement": "Entreprise",
        "Commune": {
            "Id": 29697,
            "CodeCommune": "76540",
            "LabelCrte": "CRTE Le Havre Seine Métropole – Rouen Normandie",
            "CodeCrte": "crte-28-76-15"
        },
        "code_commune": "76540"
    },
    {
        "NEj": "1510472841",
        "NPosteEj": 1,
        "DateModificationEj": "2021-01-20T00:00:00.000Z",
        "CompteBudgetaire": "Dépenses de fonction",
        "ContratEtatRegion": "#",
        "Montant": 360,
        "RefCentreCouts": {
            "Id": 96,
            "Code": "BG00/DDPP022022"
        },
        "RefCompteGeneral": {
            "Id": 11,
            "Code": "PCE/6118600000"
        },
        "RefDomaineFonctionnel": {
            "Id": 289,
            "Code": "0206-03-31"
        },
        "RefFournisseurTitulaire": {
            "Id": 14653,
            "Code": "1001348837"
        },
        "RefGroupeMarchandise": {
            "Id": 201,
            "Code": "38.02.07"
        },
        "RefLocalisationInterministerielle": {
            "Id": 2,
            "Code": "N53"
        },
        "RefProgrammation": {
            "Id": 902,
            "Code": "BG00/020603003101"
        },
        "label ref programmation": "Inspection sanitaire",
        "RefCodeProgramme": {
            "Id": 44,
            "Code": "206"
        },
        "code_programme": "206",
        "nom_programme": "Sécurité et qualité sanitaires de l'alimentation",
        "RefSiret": {
            "Id": 46790,
            "Code": "83804598700024"
        },
        "code_siret": "83804598700024",
        "nom_beneficiaire": "1HEALTHMEDIA - HEALTH INITIATIVE",
        "Theme": "Agriculture, alimentation, forêt et affaires rurales",
        "type_etablissement": "Entreprise",
        "Commune": {
            "Id": 34477,
            "CodeCommune": "92062",
            "LabelCrte": "CRTE Métropole du Grand Paris",
            "CodeCrte": "crte-11-75929394-1"
        },
        "code_commune": "92062"
    },
    {
        "NEj": "1405301631",
        "NPosteEj": 1,
        "DateModificationEj": "2021-01-20T00:00:00.000Z",
        "CompteBudgetaire": "Dépenses de fonction",
        "ContratEtatRegion": "#",
        "Montant": 1507.81,
        "RefCentreCouts": {
            "Id": 97,
            "Code": "BG00/DDPP029029"
        },
        "RefCompteGeneral": {
            "Id": 6,
            "Code": "PCE/6068800000"
        },
        "RefDomaineFonctionnel": {
            "Id": 289,
            "Code": "0206-03-31"
        },
        "RefFournisseurTitulaire": {
            "Id": 1710,
            "Code": "1000006423"
        },
        "RefGroupeMarchandise": {
            "Id": 94,
            "Code": "41.05.09"
        },
        "RefLocalisationInterministerielle": {
            "Id": 2,
            "Code": "N53"
        },
        "RefProgrammation": {
            "Id": 902,
            "Code": "BG00/020603003101"
        },
        "label ref programmation": "Inspection sanitaire",
        "RefCodeProgramme": {
            "Id": 44,
            "Code": "206"
        },
        "code_programme": "206",
        "nom_programme": "Sécurité et qualité sanitaires de l'alimentation",
        "RefSiret": {
            "Id": 26566,
            "Code": "63642033300164"
        },
        "code_siret": "63642033300164",
        "nom_beneficiaire": "FRANCE SECURITE",
        "Theme": "Agriculture, alimentation, forêt et affaires rurales",
        "type_etablissement": "Entreprise",
        "Commune": {
            "Id": 10230,
            "CodeCommune": "29019",
            "LabelCrte": "CRTE du Pays de Brest",
            "CodeCrte": "crte-53-29-2"
        },
        "code_commune": "29019"
    },
    {
        "NEj": "1405301872",
        "NPosteEj": 1,
        "DateModificationEj": "2021-01-20T00:00:00.000Z",
        "CompteBudgetaire": "Dépenses de fonction",
        "ContratEtatRegion": "#",
        "Montant": 1831.39,
        "RefCentreCouts": {
            "Id": 97,
            "Code": "BG00/DDPP029029"
        },
        "RefCompteGeneral": {
            "Id": 6,
            "Code": "PCE/6068800000"
        },
        "RefDomaineFonctionnel": {
            "Id": 289,
            "Code": "0206-03-31"
        },
        "RefFournisseurTitulaire": {
            "Id": 14646,
            "Code": "1000049312"
        },
        "RefGroupeMarchandise": {
            "Id": 94,
            "Code": "41.05.09"
        },
        "RefLocalisationInterministerielle": {
            "Id": 2,
            "Code": "N53"
        },
        "RefProgrammation": {
            "Id": 902,
            "Code": "BG00/020603003101"
        },
        "label ref programmation": "Inspection sanitaire",
        "RefCodeProgramme": {
            "Id": 44,
            "Code": "206"
        },
        "code_programme": "206",
        "nom_programme": "Sécurité et qualité sanitaires de l'alimentation",
        "RefSiret": {
            "Id": 46808,
            "Code": "39796916300047"
        },
        "code_siret": "39796916300047",
        "nom_beneficiaire": "API PROTECTION",
        "Theme": "Agriculture, alimentation, forêt et affaires rurales",
        "type_etablissement": "Entreprise",
        "Commune": {
            "Id": 27150,
            "CodeCommune": "69268",
            "LabelCrte": "CRTE de la Vallée du Garon",
            "CodeCrte": "crte-84-69-11"
        },
        "code_commune": "69268"
    },
    {
        "NEj": "1510472656",
        "NPosteEj": 1,
        "DateModificationEj": "2021-01-20T00:00:00.000Z",
        "CompteBudgetaire": "Dépenses de fonction",
        "ContratEtatRegion": "#",
        "Montant": 136.32,
        "RefCentreCouts": {
            "Id": 97,
            "Code": "BG00/DDPP029029"
        },
        "RefCompteGeneral": {
            "Id": 6,
            "Code": "PCE/6068800000"
        },
        "RefDomaineFonctionnel": {
            "Id": 289,
            "Code": "0206-03-31"
        },
        "RefFournisseurTitulaire": {
            "Id": 14641,
            "Code": "1000013032"
        },
        "RefGroupeMarchandise": {
            "Id": 6,
            "Code": "44.03.14"
        },
        "RefLocalisationInterministerielle": {
            "Id": 2,
            "Code": "N53"
        },
        "RefProgrammation": {
            "Id": 902,
            "Code": "BG00/020603003101"
        },
        "label ref programmation": "Inspection sanitaire",
        "RefCodeProgramme": {
            "Id": 44,
            "Code": "206"
        },
        "code_programme": "206",
        "nom_programme": "Sécurité et qualité sanitaires de l'alimentation",
        "RefSiret": {
            "Id": 46789,
            "Code": "37988093300021"
        },
        "code_siret": "37988093300021",
        "nom_beneficiaire": "BOBET MATERIEL",
        "Theme": "Agriculture, alimentation, forêt et affaires rurales",
        "type_etablissement": "Entreprise",
        "Commune": {
            "Id": 28335,
            "CodeCommune": "72054",
            "LabelCrte": "CRTE Le Mans Métropole",
            "CodeCrte": "crte-52-72-1"
        },
        "code_commune": "72054"
    },
    {
        "NEj": "1510472658",
        "NPosteEj": 1,
        "DateModificationEj": "2021-01-20T00:00:00.000Z",
        "CompteBudgetaire": "Dépenses de fonction",
        "ContratEtatRegion": "#",
        "Montant": 409.85,
        "RefCentreCouts": {
            "Id": 97,
            "Code": "BG00/DDPP029029"
        },
        "RefCompteGeneral": {
            "Id": 82,
            "Code": "PCE/6066610000"
        },
        "RefDomaineFonctionnel": {
            "Id": 289,
            "Code": "0206-03-31"
        },
        "RefFournisseurTitulaire": {
            "Id": 6160,
            "Code": "1000181844"
        },
        "RefGroupeMarchandise": {
            "Id": 133,
            "Code": "41.02.02"
        },
        "RefLocalisationInterministerielle": {
            "Id": 2,
            "Code": "N53"
        },
        "RefProgrammation": {
            "Id": 902,
            "Code": "BG00/020603003101"
        },
        "label ref programmation": "Inspection sanitaire",
        "RefCodeProgramme": {
            "Id": 44,
            "Code": "206"
        },
        "code_programme": "206",
        "nom_programme": "Sécurité et qualité sanitaires de l'alimentation",
        "RefSiret": {
            "Id": 35554,
            "Code": "38517576500028"
        },
        "code_siret": "38517576500028",
        "nom_beneficiaire": "SIGMA SYSTEMS SA",
        "Theme": "Agriculture, alimentation, forêt et affaires rurales",
        "type_etablissement": "Entreprise",
        "Commune": {
            "Id": 10261,
            "CodeCommune": "29051",
            "LabelCrte": "CRTE Ouest Cornouaille Odet",
            "CodeCrte": "crte-53-29-4"
        },
        "code_commune": "29051"
    },
    {
        "NEj": "1510472561",
        "NPosteEj": 1,
        "DateModificationEj": "2021-01-20T00:00:00.000Z",
        "CompteBudgetaire": "Dépenses de fonction",
        "ContratEtatRegion": "#",
        "Montant": 43.36,
        "RefCentreCouts": {
            "Id": 97,
            "Code": "BG00/DDPP029029"
        },
        "RefCompteGeneral": {
            "Id": 10,
            "Code": "PCE/6188000000"
        },
        "RefDomaineFonctionnel": {
            "Id": 289,
            "Code": "0206-03-31"
        },
        "RefFournisseurTitulaire": {
            "Id": 14641,
            "Code": "1000013032"
        },
        "RefGroupeMarchandise": {
            "Id": 10,
            "Code": "45.05.07"
        },
        "RefLocalisationInterministerielle": {
            "Id": 2,
            "Code": "N53"
        },
        "RefProgrammation": {
            "Id": 902,
            "Code": "BG00/020603003101"
        },
        "label ref programmation": "Inspection sanitaire",
        "RefCodeProgramme": {
            "Id": 44,
            "Code": "206"
        },
        "code_programme": "206",
        "nom_programme": "Sécurité et qualité sanitaires de l'alimentation",
        "RefSiret": {
            "Id": 46789,
            "Code": "37988093300021"
        },
        "code_siret": "37988093300021",
        "nom_beneficiaire": "BOBET MATERIEL",
        "Theme": "Agriculture, alimentation, forêt et affaires rurales",
        "type_etablissement": "Entreprise",
        "Commune": {
            "Id": 28335,
            "CodeCommune": "72054",
            "LabelCrte": "CRTE Le Mans Métropole",
            "CodeCrte": "crte-52-72-1"
        },
        "code_commune": "72054"
    },
    {
        "NEj": "2201272909",
        "NPosteEj": 1,
        "DateModificationEj": "2021-01-21T00:00:00.000Z",
        "CompteBudgetaire": "Transferts aux entre",
        "ContratEtatRegion": "#",
        "Montant": 250,
        "RefCentreCouts": {
            "Id": 95,
            "Code": "BG00/DDCC035035"
        },
        "RefCompteGeneral": {
            "Id": 13,
            "Code": "PCE/6521400000"
        },
        "RefDomaineFonctionnel": {
            "Id": 290,
            "Code": "0206-03-33"
        },
        "RefFournisseurTitulaire": {
            "Id": 14656,
            "Code": "1000874335"
        },
        "RefGroupeMarchandise": {
            "Id": 13,
            "Code": "08.03.01"
        },
        "RefLocalisationInterministerielle": {
            "Id": 2,
            "Code": "N53"
        },
        "RefProgrammation": {
            "Id": 903,
            "Code": "BG00/020603003301"
        },
        "label ref programmation": "Lutte vs zoonoses",
        "RefCodeProgramme": {
            "Id": 44,
            "Code": "206"
        },
        "code_programme": "206",
        "nom_programme": "Sécurité et qualité sanitaires de l'alimentation",
        "RefSiret": {
            "Id": 46817,
            "Code": "75397110000023"
        },
        "code_siret": "75397110000023",
        "nom_beneficiaire": "AMILLY ACCOUVAGE",
        "Theme": "Agriculture, alimentation, forêt et affaires rurales",
        "type_etablissement": "Entreprise",
        "Commune": {
            "Id": 16360,
            "CodeCommune": "45004",
            "LabelCrte": "CRTE Gâtinais Montargois",
            "CodeCrte": "crte-24-45-6"
        },
        "code_commune": "45004"
    },
    {
        "NEj": "2201272901",
        "NPosteEj": 1,
        "DateModificationEj": "2021-01-21T00:00:00.000Z",
        "CompteBudgetaire": "Transferts aux entre",
        "ContratEtatRegion": "#",
        "Montant": 250,
        "RefCentreCouts": {
            "Id": 95,
            "Code": "BG00/DDCC035035"
        },
        "RefCompteGeneral": {
            "Id": 13,
            "Code": "PCE/6521400000"
        },
        "RefDomaineFonctionnel": {
            "Id": 290,
            "Code": "0206-03-33"
        },
        "RefFournisseurTitulaire": {
            "Id": 14656,
            "Code": "1000874335"
        },
        "RefGroupeMarchandise": {
            "Id": 13,
            "Code": "08.03.01"
        },
        "RefLocalisationInterministerielle": {
            "Id": 2,
            "Code": "N53"
        },
        "RefProgrammation": {
            "Id": 903,
            "Code": "BG00/020603003301"
        },
        "label ref programmation": "Lutte vs zoonoses",
        "RefCodeProgramme": {
            "Id": 44,
            "Code": "206"
        },
        "code_programme": "206",
        "nom_programme": "Sécurité et qualité sanitaires de l'alimentation",
        "RefSiret": {
            "Id": 46817,
            "Code": "75397110000023"
        },
        "code_siret": "75397110000023",
        "nom_beneficiaire": "AMILLY ACCOUVAGE",
        "Theme": "Agriculture, alimentation, forêt et affaires rurales",
        "type_etablissement": "Entreprise",
        "Commune": {
            "Id": 16360,
            "CodeCommune": "45004",
            "LabelCrte": "CRTE Gâtinais Montargois",
            "CodeCrte": "crte-24-45-6"
        },
        "code_commune": "45004"
    },
    {
        "NEj": "2201272903",
        "NPosteEj": 1,
        "DateModificationEj": "2021-01-21T00:00:00.000Z",
        "CompteBudgetaire": "Transferts aux entre",
        "ContratEtatRegion": "#",
        "Montant": 360,
        "RefCentreCouts": {
            "Id": 95,
            "Code": "BG00/DDCC035035"
        },
        "RefCompteGeneral": {
            "Id": 13,
            "Code": "PCE/6521400000"
        },
        "RefDomaineFonctionnel": {
            "Id": 290,
            "Code": "0206-03-33"
        },
        "RefFournisseurTitulaire": {
            "Id": 14661,
            "Code": "1000484116"
        },
        "RefGroupeMarchandise": {
            "Id": 13,
            "Code": "08.03.01"
        },
        "RefLocalisationInterministerielle": {
            "Id": 2,
            "Code": "N53"
        },
        "RefProgrammation": {
            "Id": 903,
            "Code": "BG00/020603003301"
        },
        "label ref programmation": "Lutte vs zoonoses",
        "RefCodeProgramme": {
            "Id": 44,
            "Code": "206"
        },
        "code_programme": "206",
        "nom_programme": "Sécurité et qualité sanitaires de l'alimentation",
        "RefSiret": {
            "Id": 46825,
            "Code": "52535602800023"
        },
        "code_siret": "52535602800023",
        "nom_beneficiaire": "AVIAGEN FRANCE",
        "Theme": "Agriculture, alimentation, forêt et affaires rurales",
        "type_etablissement": "Entreprise",
        "Commune": {
            "Id": 17478,
            "CodeCommune": "49020",
            "LabelCrte": "CRTE Angers Loire Métropole",
            "CodeCrte": "crte-52-49-2"
        },
        "code_commune": "49020"
    },
    {
        "NEj": "2201272907",
        "NPosteEj": 1,
        "DateModificationEj": "2021-01-21T00:00:00.000Z",
        "CompteBudgetaire": "Transferts aux entre",
        "ContratEtatRegion": "#",
        "Montant": 250,
        "RefCentreCouts": {
            "Id": 95,
            "Code": "BG00/DDCC035035"
        },
        "RefCompteGeneral": {
            "Id": 13,
            "Code": "PCE/6521400000"
        },
        "RefDomaineFonctionnel": {
            "Id": 290,
            "Code": "0206-03-33"
        },
        "RefFournisseurTitulaire": {
            "Id": 14655,
            "Code": "1000446476"
        },
        "RefGroupeMarchandise": {
            "Id": 13,
            "Code": "08.03.01"
        },
        "RefLocalisationInterministerielle": {
            "Id": 2,
            "Code": "N53"
        },
        "RefProgrammation": {
            "Id": 903,
            "Code": "BG00/020603003301"
        },
        "label ref programmation": "Lutte vs zoonoses",
        "RefCodeProgramme": {
            "Id": 44,
            "Code": "206"
        },
        "code_programme": "206",
        "nom_programme": "Sécurité et qualité sanitaires de l'alimentation",
        "RefSiret": {
            "Id": 46821,
            "Code": "34751725200024"
        },
        "code_siret": "34751725200024",
        "nom_beneficiaire": "GALINA PERROT",
        "Theme": "Agriculture, alimentation, forêt et affaires rurales",
        "type_etablissement": "Entreprise",
        "Commune": {
            "Id": 7502,
            "CodeCommune": "22264",
            "LabelCrte": "CRTE Lannion-Trégor Communauté",
            "CodeCrte": "crte-53-22-5"
        },
        "code_commune": "22264"
    },
    {
        "NEj": "2201272890",
        "NPosteEj": 1,
        "DateModificationEj": "2021-01-22T00:00:00.000Z",
        "CompteBudgetaire": "Transferts aux entre",
        "ContratEtatRegion": "#",
        "Montant": 270,
        "RefCentreCouts": {
            "Id": 95,
            "Code": "BG00/DDCC035035"
        },
        "RefCompteGeneral": {
            "Id": 13,
            "Code": "PCE/6521400000"
        },
        "RefDomaineFonctionnel": {
            "Id": 290,
            "Code": "0206-03-33"
        },
        "RefFournisseurTitulaire": {
            "Id": 14660,
            "Code": "1001381774"
        },
        "RefGroupeMarchandise": {
            "Id": 13,
            "Code": "08.03.01"
        },
        "RefLocalisationInterministerielle": {
            "Id": 2,
            "Code": "N53"
        },
        "RefProgrammation": {
            "Id": 903,
            "Code": "BG00/020603003301"
        },
        "label ref programmation": "Lutte vs zoonoses",
        "RefCodeProgramme": {
            "Id": 44,
            "Code": "206"
        },
        "code_programme": "206",
        "nom_programme": "Sécurité et qualité sanitaires de l'alimentation",
        "RefSiret": {
            "Id": 46826,
            "Code": "50739854300029"
        },
        "code_siret": "50739854300029",
        "nom_beneficiaire": "NOVOGEN",
        "Theme": "Agriculture, alimentation, forêt et affaires rurales",
        "type_etablissement": "Entreprise",
        "Commune": {
            "Id": 7420,
            "CodeCommune": "22176",
            "LabelCrte": "CRTE Saint-Brieuc Armor Agglomération",
            "CodeCrte": "crte-53-22-6"
        },
        "code_commune": "22176"
    },
    {
        "NEj": "1510477005",
        "NPosteEj": 1,
        "DateModificationEj": "2021-01-22T00:00:00.000Z",
        "CompteBudgetaire": "Dépenses de fonction",
        "ContratEtatRegion": "#",
        "Montant": 562.8,
        "RefCentreCouts": {
            "Id": 95,
            "Code": "BG00/DDCC035035"
        },
        "RefCompteGeneral": {
            "Id": 6,
            "Code": "PCE/6068800000"
        },
        "RefDomaineFonctionnel": {
            "Id": 289,
            "Code": "0206-03-31"
        },
        "RefFournisseurTitulaire": {
            "Id": 1718,
            "Code": "1000084908"
        },
        "RefGroupeMarchandise": {
            "Id": 6,
            "Code": "44.03.14"
        },
        "RefLocalisationInterministerielle": {
            "Id": 2,
            "Code": "N53"
        },
        "RefProgrammation": {
            "Id": 902,
            "Code": "BG00/020603003101"
        },
        "label ref programmation": "Inspection sanitaire",
        "RefCodeProgramme": {
            "Id": 44,
            "Code": "206"
        },
        "code_programme": "206",
        "nom_programme": "Sécurité et qualité sanitaires de l'alimentation",
        "RefSiret": {
            "Id": 26632,
            "Code": "32929506700022"
        },
        "code_siret": "32929506700022",
        "nom_beneficiaire": "SOCIETE COOL",
        "Theme": "Agriculture, alimentation, forêt et affaires rurales",
        "type_etablissement": "Entreprise",
        "Commune": {
            "Id": 2357,
            "CodeCommune": "07349",
            "LabelCrte": "CRTE Centre-Nord Ardèche",
            "CodeCrte": "crte-84-07-2"
        },
        "code_commune": "07349"
    },
    {
        "NEj": "2201274267",
        "NPosteEj": 1,
        "DateModificationEj": "2021-01-22T00:00:00.000Z",
        "CompteBudgetaire": "Transferts aux entre",
        "ContratEtatRegion": "#",
        "Montant": 500,
        "RefCentreCouts": {
            "Id": 95,
            "Code": "BG00/DDCC035035"
        },
        "RefCompteGeneral": {
            "Id": 13,
            "Code": "PCE/6521400000"
        },
        "RefDomaineFonctionnel": {
            "Id": 290,
            "Code": "0206-03-33"
        },
        "RefFournisseurTitulaire": {
            "Id": 14662,
            "Code": "1000357211"
        },
        "RefGroupeMarchandise": {
            "Id": 13,
            "Code": "08.03.01"
        },
        "RefLocalisationInterministerielle": {
            "Id": 2,
            "Code": "N53"
        },
        "RefProgrammation": {
            "Id": 903,
            "Code": "BG00/020603003301"
        },
        "label ref programmation": "Lutte vs zoonoses",
        "RefCodeProgramme": {
            "Id": 44,
            "Code": "206"
        },
        "code_programme": "206",
        "nom_programme": "Sécurité et qualité sanitaires de l'alimentation",
        "RefSiret": {
            "Id": 46818,
            "Code": "30560939800030"
        },
        "code_siret": "30560939800030",
        "nom_beneficiaire": "HUBBARD",
        "Theme": "Agriculture, alimentation, forêt et affaires rurales",
        "type_etablissement": "Entreprise",
        "Commune": {
            "Id": 7319,
            "CodeCommune": "22059",
            "LabelCrte": "CRTE Saint-Brieuc Armor Agglomération",
            "CodeCrte": "crte-53-22-6"
        },
        "code_commune": "22059"
    },
    {
        "NEj": "2201272874",
        "NPosteEj": 1,
        "DateModificationEj": "2021-01-22T00:00:00.000Z",
        "CompteBudgetaire": "Transferts aux entre",
        "ContratEtatRegion": "#",
        "Montant": 360,
        "RefCentreCouts": {
            "Id": 95,
            "Code": "BG00/DDCC035035"
        },
        "RefCompteGeneral": {
            "Id": 13,
            "Code": "PCE/6521400000"
        },
        "RefDomaineFonctionnel": {
            "Id": 290,
            "Code": "0206-03-33"
        },
        "RefFournisseurTitulaire": {
            "Id": 14655,
            "Code": "1000446476"
        },
        "RefGroupeMarchandise": {
            "Id": 13,
            "Code": "08.03.01"
        },
        "RefLocalisationInterministerielle": {
            "Id": 2,
            "Code": "N53"
        },
        "RefProgrammation": {
            "Id": 903,
            "Code": "BG00/020603003301"
        },
        "label ref programmation": "Lutte vs zoonoses",
        "RefCodeProgramme": {
            "Id": 44,
            "Code": "206"
        },
        "code_programme": "206",
        "nom_programme": "Sécurité et qualité sanitaires de l'alimentation",
        "RefSiret": {
            "Id": 46821,
            "Code": "34751725200024"
        },
        "code_siret": "34751725200024",
        "nom_beneficiaire": "GALINA PERROT",
        "Theme": "Agriculture, alimentation, forêt et affaires rurales",
        "type_etablissement": "Entreprise",
        "Commune": {
            "Id": 7502,
            "CodeCommune": "22264",
            "LabelCrte": "CRTE Lannion-Trégor Communauté",
            "CodeCrte": "crte-53-22-5"
        },
        "code_commune": "22264"
    },
    {
        "NEj": "1510476874",
        "NPosteEj": 1,
        "DateModificationEj": "2021-01-22T00:00:00.000Z",
        "CompteBudgetaire": "Dépenses de fonction",
        "ContratEtatRegion": "#",
        "Montant": 819.01,
        "RefCentreCouts": {
            "Id": 95,
            "Code": "BG00/DDCC035035"
        },
        "RefCompteGeneral": {
            "Id": 6,
            "Code": "PCE/6068800000"
        },
        "RefDomaineFonctionnel": {
            "Id": 289,
            "Code": "0206-03-31"
        },
        "RefFournisseurTitulaire": {
            "Id": 14637,
            "Code": "1001289656"
        },
        "RefGroupeMarchandise": {
            "Id": 6,
            "Code": "44.03.14"
        },
        "RefLocalisationInterministerielle": {
            "Id": 2,
            "Code": "N53"
        },
        "RefProgrammation": {
            "Id": 902,
            "Code": "BG00/020603003101"
        },
        "label ref programmation": "Inspection sanitaire",
        "RefCodeProgramme": {
            "Id": 44,
            "Code": "206"
        },
        "code_programme": "206",
        "nom_programme": "Sécurité et qualité sanitaires de l'alimentation",
        "RefSiret": {
            "Id": 46801,
            "Code": "85720088500278"
        },
        "code_siret": "85720088500278",
        "nom_beneficiaire": "LABELIANS",
        "Theme": "Agriculture, alimentation, forêt et affaires rurales",
        "type_etablissement": "Entreprise",
        "Commune": {
            "Id": 30218,
            "CodeCommune": "77333",
            "LabelCrte": "CRTE Pays de Nemours",
            "CodeCrte": "crte-11-77-9"
        },
        "code_commune": "77333"
    },
    {
        "NEj": "2201272885",
        "NPosteEj": 1,
        "DateModificationEj": "2021-01-22T00:00:00.000Z",
        "CompteBudgetaire": "Transferts aux entre",
        "ContratEtatRegion": "#",
        "Montant": 180,
        "RefCentreCouts": {
            "Id": 95,
            "Code": "BG00/DDCC035035"
        },
        "RefCompteGeneral": {
            "Id": 13,
            "Code": "PCE/6521400000"
        },
        "RefDomaineFonctionnel": {
            "Id": 290,
            "Code": "0206-03-33"
        },
        "RefFournisseurTitulaire": {
            "Id": 14657,
            "Code": "1000356815"
        },
        "RefGroupeMarchandise": {
            "Id": 13,
            "Code": "08.03.01"
        },
        "RefLocalisationInterministerielle": {
            "Id": 2,
            "Code": "N53"
        },
        "RefProgrammation": {
            "Id": 903,
            "Code": "BG00/020603003301"
        },
        "label ref programmation": "Lutte vs zoonoses",
        "RefCodeProgramme": {
            "Id": 44,
            "Code": "206"
        },
        "code_programme": "206",
        "nom_programme": "Sécurité et qualité sanitaires de l'alimentation",
        "RefSiret": {
            "Id": 46829,
            "Code": "33806964400015"
        },
        "code_siret": "33806964400015",
        "nom_beneficiaire": "EARL COUVOIR DE L'AUSIER",
        "Theme": "Agriculture, alimentation, forêt et affaires rurales",
        "type_etablissement": "Entreprise",
        "Commune": {
            "Id": 13272,
            "CodeCommune": "35162",
            "LabelCrte": "CRTE Fougères Agglomération",
            "CodeCrte": "crte-53-35-15"
        },
        "code_commune": "35162"
    },
    {
        "NEj": "2201272895",
        "NPosteEj": 1,
        "DateModificationEj": "2021-01-22T00:00:00.000Z",
        "CompteBudgetaire": "Transferts aux entre",
        "ContratEtatRegion": "#",
        "Montant": 90,
        "RefCentreCouts": {
            "Id": 95,
            "Code": "BG00/DDCC035035"
        },
        "RefCompteGeneral": {
            "Id": 13,
            "Code": "PCE/6521400000"
        },
        "RefDomaineFonctionnel": {
            "Id": 290,
            "Code": "0206-03-33"
        },
        "RefFournisseurTitulaire": {
            "Id": 14660,
            "Code": "1001381774"
        },
        "RefGroupeMarchandise": {
            "Id": 13,
            "Code": "08.03.01"
        },
        "RefLocalisationInterministerielle": {
            "Id": 2,
            "Code": "N53"
        },
        "RefProgrammation": {
            "Id": 903,
            "Code": "BG00/020603003301"
        },
        "label ref programmation": "Lutte vs zoonoses",
        "RefCodeProgramme": {
            "Id": 44,
            "Code": "206"
        },
        "code_programme": "206",
        "nom_programme": "Sécurité et qualité sanitaires de l'alimentation",
        "RefSiret": {
            "Id": 46826,
            "Code": "50739854300029"
        },
        "code_siret": "50739854300029",
        "nom_beneficiaire": "NOVOGEN",
        "Theme": "Agriculture, alimentation, forêt et affaires rurales",
        "type_etablissement": "Entreprise",
        "Commune": {
            "Id": 7420,
            "CodeCommune": "22176",
            "LabelCrte": "CRTE Saint-Brieuc Armor Agglomération",
            "CodeCrte": "crte-53-22-6"
        },
        "code_commune": "22176"
    }
]